ndi_formatter/__init__.py
ndi_formatter/attributes.py
ndi_formatter/format.py
ndi_formatter/lookup.py
ndi_formatter/utils.py
ndi_formatter/validate.py
ndi_formatter-1.1.0.dist-info/entry_points.txt
ndi_formatter-1.1.0.dist-info/LICENSE
ndi_formatter-1.1.0.dist-info/WHEEL
ndi_formatter-1.1.0.dist-info/METADATA
ndi_formatter-1.1.0.dist-info/RECORD
