Metadata-Version: 2.1
Name: ndi_formatter
Version: 1.1.0
Summary: Format data for National Death Index (NDI) requests.
Keywords: nlp,information extraction
Author-email: dcronkite <dcronkite+pypi@gmail.com>
Requires-Python: >=3.6
Classifier: Development Status :: 5 - Production/Stable
Classifier: Intended Audience :: Science/Research
Classifier: Programming Language :: Python :: 3 :: Only
Requires-Dist: dateutil ; extra == "date"
Requires-Dist: sas7bdat ; extra == "sas"
Project-URL: Home, https://github.com/kpwhri/ndi_formatter
Provides-Extra: date
Provides-Extra: sas
